dca/__init__.py
dca/analysis.py
dca/base.py
dca/cov_util.py
dca/data_util.py
dca/dca.py
dca/knn.py
dca/methods_comparison.py
dca/style.py
dca/synth_data.py
dca/plotting/__init__.py
dca/plotting/fig1.py
dca/plotting/fig2.py
dynamicalcomponentsanalysis-1.1.0.dist-info/licenses/LICENSE.txt
dynamicalcomponentsanalysis-1.1.0.dist-info/METADATA
dynamicalcomponentsanalysis-1.1.0.dist-info/WHEEL
dynamicalcomponentsanalysis-1.1.0.dist-info/top_level.txt
dynamicalcomponentsanalysis-1.1.0.dist-info/RECORD
