Metadata-Version: 2.4
Name: DynamicalComponentsAnalysis
Version: 1.1.0
Summary: Dynamical Components Analysis
Author-email: Jesse Livezey <jesse.livezey@gmail.com>, David Clark <dgc2138@cumc.columbia.edu>
License: *** License Agreement ***
Project-URL: Homepage, https://github.com/BouchardLab/DynamicalComponentsAnalysis
Project-URL: Bug Tracker, https://github.com/BouchardLab/DynamicalComponentsAnalysis/issues
Classifier: Programming Language :: Python :: 3
Classifier: Operating System :: OS Independent
Requires-Python: >=3.6
License-File: LICENSE.txt
Requires-Dist: numpy
Requires-Dist: scipy
Requires-Dist: h5py
Requires-Dist: pandas
Requires-Dist: scikit-learn
Requires-Dist: matplotlib
Requires-Dist: torch
Dynamic: license-file
